pawnstack/__init__.py
pawnstack/__main__.py
pawnstack/__version__.py
pawnstack/async_utils/__init__.py
pawnstack/async_utils/helper.py
pawnstack/async_utils/tasks.py
pawnstack/builder/__init__.py
pawnstack/builder/generator.py
pawnstack/builder/templates/app_with_logging.tmpl
pawnstack/cli/__init__.py
pawnstack/cli/aws.py
pawnstack/cli/banner.py
pawnstack/cli/base.py
pawnstack/cli/compose.py
pawnstack/cli/dependencies.py
pawnstack/cli/deps.py
pawnstack/cli/docker.py
pawnstack/cli/file.py
pawnstack/cli/formatter.py
pawnstack/cli/http.py
pawnstack/cli/icon.py
pawnstack/cli/info.py
pawnstack/cli/init.py
pawnstack/cli/inspect.py
pawnstack/cli/main.py
pawnstack/cli/mon.py
pawnstack/cli/net.py
pawnstack/cli/noti.py
pawnstack/cli/parser.py
pawnstack/cli/proxy.py
pawnstack/cli/rpc.py
pawnstack/cli/s3.py
pawnstack/cli/scan_key.py
pawnstack/cli/server.py
pawnstack/cli/top.py
pawnstack/cli/top_standalone.py
pawnstack/cli/websocket.py
pawnstack/cli/commands/__init__.py
pawnstack/cli/commands/http.py
pawnstack/cli/commands/system.py
pawnstack/config/__init__.py
pawnstack/config/global_config.py
pawnstack/config/settings.py
pawnstack/core/__init__.py
pawnstack/core/base.py
pawnstack/core/mixins.py
pawnstack/docker/__init__.py
pawnstack/docker/async_client.py
pawnstack/docker/compose.py
pawnstack/exceptions/__init__.py
pawnstack/http_client/__init__.py
pawnstack/http_client/client.py
pawnstack/input/__init__.py
pawnstack/log/___________logger.py
pawnstack/log/__init__.py
pawnstack/models/__init__.py
pawnstack/monitoring/__init__.py
pawnstack/monitoring/benchmark.py
pawnstack/monitoring/http_monitor.py
pawnstack/monitoring/performance.py
pawnstack/monitoring/tracker.py
pawnstack/output/__init__.py
pawnstack/resource/__init__.py
pawnstack/resource/disk.py
pawnstack/resource/network.py
pawnstack/resource/system.py
pawnstack/system/__init__.py
pawnstack/system/monitor.py
pawnstack/type_utils/__init__.py
pawnstack/type_utils/constants.py
pawnstack/type_utils/converters.py
pawnstack-1.0.0.dist-info/METADATA
pawnstack-1.0.0.dist-info/WHEEL
pawnstack-1.0.0.dist-info/entry_points.txt
pawnstack-1.0.0.dist-info/RECORD
