Metadata-Version: 2.4
Name: pawnstack
Version: 1.0.0
Summary: pawnstack: A modern Python library for Infrastructure as Code (IaC), offering tools for system monitoring, HTTP utilities, and more.
Project-URL: Changelog, https://github.com/JINWOO-J/pawnstack/blob/main/CHANGELOG.md
Project-URL: Documentation, https://pawnstack.readthedocs.io
Project-URL: Homepage, https://pawnstack.readthedocs.io
Project-URL: Source, https://github.com/JINWOO-J/pawnstack
Author-email: Jinwoo <jinwoo@parametacorp.com>
License: MIT License
Keywords: Infrastructure as Code,Python IaC,pawnstack tools,system monitoring
Classifier: Development Status :: 4 - Beta
Classifier: Environment :: Console
Classifier: Intended Audience :: Developers
Classifier: License :: OSI Approved :: MIT License
Classifier: Operating System :: OS Independent
Classifier: Programming Language :: Python :: 3
Classifier: Programming Language :: Python :: 3 :: Only
Classifier: Programming Language :: Python :: 3.9
Classifier: Programming Language :: Python :: 3.10
Classifier: Programming Language :: Python :: 3.11
Classifier: Programming Language :: Python :: 3.12
Classifier: Topic :: Internet :: WWW/HTTP
Classifier: Topic :: Software Development :: Libraries :: Python Modules
Classifier: Topic :: System :: Monitoring
Classifier: Topic :: System :: Systems Administration
Requires-Python: >=3.9
Requires-Dist: aiofiles>=23.0.0
Requires-Dist: aiohttp>=3.8.6
Requires-Dist: aiometer>=0.3.0
Requires-Dist: certifi>=2023.7.22
Requires-Dist: charset-normalizer>=3.3.0
Requires-Dist: dnspython>=2.4.0
Requires-Dist: httpx<1.0.0,>=0.25.0
Requires-Dist: idna>=3.4
Requires-Dist: jinja2>=3.1.0
Requires-Dist: parameterized>=0.9.0
Requires-Dist: psutil>=5.9.0
Requires-Dist: pydantic<3.0.0,>=2.0.0
Requires-Dist: pyfiglet>=1.0.0
Requires-Dist: python-dotenv>=1.0.0
Requires-Dist: pyyaml>=6.0.1
Requires-Dist: requests>=2.31.0
Requires-Dist: rich<15.0.0,>=13.0.0
Requires-Dist: tabulate>=0.9.0
Requires-Dist: tqdm>=4.66.0
Requires-Dist: typer<1.0.0,>=0.9.0
Requires-Dist: urllib3>=2.0.0
Requires-Dist: websocket-client>=1.6.0
Provides-Extra: blockchain
Requires-Dist: coincurve<19.0.0,>=18.0.0; extra == 'blockchain'
Requires-Dist: eth-keyfile<1.0.0,>=0.7.0; extra == 'blockchain'
Requires-Dist: secp256k1<1.0.0,>=0.14.0; extra == 'blockchain'
Provides-Extra: cloud
Requires-Dist: aioboto3<12.0.0,>=11.0.0; extra == 'cloud'
Requires-Dist: boto3<2.0.0,>=1.34.0; extra == 'cloud'
Provides-Extra: database
Requires-Dist: aiomysql<1.0.0,>=0.2.0; extra == 'database'
Requires-Dist: asyncpg<1.0.0,>=0.29.0; extra == 'database'
Requires-Dist: sqlalchemy<3.0.0,>=2.0.0; extra == 'database'
Provides-Extra: docker
Requires-Dist: aiodocker<1.0.0,>=0.21.0; extra == 'docker'
Provides-Extra: full
Requires-Dist: aioboto3<12.0.0,>=11.0.0; extra == 'full'
Requires-Dist: aiodocker<1.0.0,>=0.21.0; extra == 'full'
Requires-Dist: aiomysql<1.0.0,>=0.2.0; extra == 'full'
Requires-Dist: aioredis<3.0.0,>=2.0.0; extra == 'full'
Requires-Dist: asyncpg<1.0.0,>=0.29.0; extra == 'full'
Requires-Dist: boto3<2.0.0,>=1.34.0; extra == 'full'
Requires-Dist: coincurve<19.0.0,>=18.0.0; extra == 'full'
Requires-Dist: discord-py<3.0.0,>=2.3.0; extra == 'full'
Requires-Dist: eth-keyfile<1.0.0,>=0.7.0; extra == 'full'
Requires-Dist: grafana-api<2.0.0,>=1.0.0; extra == 'full'
Requires-Dist: msgpack<2.0.0,>=1.0.0; extra == 'full'
Requires-Dist: orjson<4.0.0,>=3.9.0; extra == 'full'
Requires-Dist: prometheus-client<1.0.0,>=0.19.0; extra == 'full'
Requires-Dist: redis<6.0.0,>=5.0.0; extra == 'full'
Requires-Dist: secp256k1<1.0.0,>=0.14.0; extra == 'full'
Requires-Dist: slack-sdk<4.0.0,>=3.27.0; extra == 'full'
Requires-Dist: sqlalchemy<3.0.0,>=2.0.0; extra == 'full'
Requires-Dist: uvloop<1.0.0,>=0.19.0; (sys_platform != 'win32') and extra == 'full'
Provides-Extra: messaging
Requires-Dist: discord-py<3.0.0,>=2.3.0; extra == 'messaging'
Requires-Dist: slack-sdk<4.0.0,>=3.27.0; extra == 'messaging'
Provides-Extra: monitoring
Requires-Dist: grafana-api<2.0.0,>=1.0.0; extra == 'monitoring'
Requires-Dist: prometheus-client<1.0.0,>=0.19.0; extra == 'monitoring'
Provides-Extra: performance
Requires-Dist: msgpack<2.0.0,>=1.0.0; extra == 'performance'
Requires-Dist: orjson<4.0.0,>=3.9.0; extra == 'performance'
Requires-Dist: uvloop<1.0.0,>=0.19.0; (sys_platform != 'win32') and extra == 'performance'
Provides-Extra: redis
Requires-Dist: aioredis<3.0.0,>=2.0.0; extra == 'redis'
Requires-Dist: redis<6.0.0,>=5.0.0; extra == 'redis'
